drupal_dockerizer/__init__.py
drupal_dockerizer/appconfig.py
drupal_dockerizer/cli.py
drupal_dockerizer/dependency.py
drupal_dockerizer/dockerizer.py
drupal_dockerizer/dockerizer_config.py
drupal_dockerizer/network.py
drupal_dockerizer/playbook.py
drupal_dockerizer-0.0.5.dist-info/LICENSE.md
drupal_dockerizer-0.0.5.dist-info/METADATA
drupal_dockerizer-0.0.5.dist-info/WHEEL
drupal_dockerizer-0.0.5.dist-info/entry_points.txt
drupal_dockerizer-0.0.5.dist-info/top_level.txt
drupal_dockerizer-0.0.5.dist-info/RECORD
