Metadata-Version: 2.1
Name: drupal-dockerizer
Version: 0.0.5
Summary: Cli tool for up drupal projects in docker containers
Home-page: https://github.com/jet-dev-team/drupal-dockerizer-cli
Author: Vladislav Sadretdinov
Author-email: svicervlad@gmail.com
License: UNKNOWN
Platform: UNKNOWN
Classifier: Programming Language :: Python :: 3
Classifier: License :: OSI Approved :: MIT License
Classifier: Operating System :: OS Independent
Requires-Python: >=3.8
Requires-Dist: Click
Requires-Dist: appdirs
Requires-Dist: PyYAML
Requires-Dist: wheel
Requires-Dist: requests
Requires-Dist: tabulate
